Metadata-Version: 1.0
Name: stacktools
Version: 0.1.2
Summary: data prep
Home-page: http://github.com/mrmh2/stacktools
Author: Matthew Hartley
Author-email: mhartley@cantab.net
License: MIT
Platform: UNKNOWN
